gllm_rag/__init__.pyi
gllm_rag/preset/__init__.pyi
gllm_rag/preset/initializer/__init__.pyi
gllm_rag/preset/initializer/data_store.pyi
gllm_rag/preset/initializer/em_invoker.pyi
gllm_rag/preset/initializer/lm_invoker.pyi
gllm_rag/preset/initializer/model_id.pyi
gllm_rag/preset/lm.pyi
gllm_rag/preset/pipeline_preset.pyi
gllm_rag/preset/simple_rag.pyi
gllm_rag.build/.gitignore
gllm_rag.cpython-311-x86_64-linux-gnu.so
gllm_rag.pyi
gllm_rag_binary-0.0.2.dist-info/METADATA
gllm_rag_binary-0.0.2.dist-info/WHEEL
gllm_rag_binary-0.0.2.dist-info/RECORD
