Metadata-Version: 2.1
Name: gllm-rag-binary
Version: 0.0.2
Summary: A library containing RAG pipeline builders and presets for Gen AI applications.
Author: Dimitrij Ray
Author-email: dimitrij.ray@gdplabs.id
Requires-Python: >=3.11,<3.13
Classifier: Programming Language :: Python :: 3
Classifier: Programming Language :: Python :: 3.11
Classifier: Programming Language :: Python :: 3.12
Requires-Dist: gllm-core-binary
Requires-Dist: gllm-datastore-binary[chroma,elasticsearch]
Requires-Dist: gllm-generation-binary
Requires-Dist: gllm-inference-binary[anthropic,google-genai,google-vertexai,openai]
Requires-Dist: gllm-misc-binary
Requires-Dist: gllm-pipeline-binary
Requires-Dist: gllm-retrieval-binary[elasticsearch,flag-embedding,sql]
Requires-Dist: libmagic (>=1.0,<2.0) ; sys_platform == "win32"
Requires-Dist: python-dotenv (>=1.0.1,<2.0.0)
Requires-Dist: python-magic-bin (>=0.4.14,<0.5.0) ; sys_platform == "win32"
Requires-Dist: strictyaml (>=1.7,<2.0)
